README.txt
setup.cfg
setup.py
src/islay/__init__.py
src/islay.auth.egg-info/PKG-INFO
src/islay.auth.egg-info/SOURCES.txt
src/islay.auth.egg-info/dependency_links.txt
src/islay.auth.egg-info/entry_points.txt
src/islay.auth.egg-info/namespace_packages.txt
src/islay.auth.egg-info/not-zip-safe
src/islay.auth.egg-info/requires.txt
src/islay.auth.egg-info/top_level.txt
src/islay/auth/__init__.py
src/islay/auth/auth.py
src/islay/auth/examples.py
src/islay/auth/interfaces.py
src/islay/auth/tests/__init__.py
src/islay/auth/tests/base.py
src/islay/auth/tests/test_auth.py
src/islay/auth/tests/test_forbidden.py