Metadata-Version: 1.0
Name: islay.auth
Version: 0.1
Summary: An unobtrusive authentication framework for WSGI stacks.
Home-page: http://code.google.com/p/islay/
Author: Matthew Wilkes
Author-email: wilkes@jarn.com
License: Modified BSD
Keywords: wsgi python authentication repoze.who
Platform: UNKNOWN
Classifier: Programming Language :: Python
Classifier: Topic :: Software Development :: Libraries :: Python Modules
Classifier: License :: OSI Approved :: BSD License
Classifier: Topic :: Internet :: WWW/HTTP :: WSGI :: Middleware
Classifier: Topic :: Security
